napari_organoid_counter/__init__.py
napari_organoid_counter/_orgacount.py
napari_organoid_counter/_reader.py
napari_organoid_counter/_utils.py
napari_organoid_counter/_version.py
napari_organoid_counter/_widget.py
napari_organoid_counter/napari.yaml
napari_organoid_counter/settings.py
napari_organoid_counter/_tests/__init__.py
napari_organoid_counter/_tests/test_orgacount.py
napari_organoid_counter/_tests/test_reader.py
napari_organoid_counter/_tests/test_utils.py
napari_organoid_counter/_tests/test_widget.py
napari_organoid_counter-0.2.5.dist-info/LICENSE
napari_organoid_counter-0.2.5.dist-info/METADATA
napari_organoid_counter-0.2.5.dist-info/WHEEL
napari_organoid_counter-0.2.5.dist-info/entry_points.txt
napari_organoid_counter-0.2.5.dist-info/top_level.txt
napari_organoid_counter-0.2.5.dist-info/RECORD
