Metadata-Version: 2.1
Name: napari-organoid-counter
Version: 0.2.5
Summary: A plugin to automatically count lung organoids using Deep Learning.
Home-page: https://github.com/HelmholtzAI-Consultants-Munich/napari-organoid-counter
Author: christinab12
Author-email: christina.bukas@helmholtz-muenchen.de
License: MIT
Project-URL: Bug Tracker, https://github.com/HelmholtzAI-Consultants-Munich/napari-organoid-counter/issues
Project-URL: Documentation, https://github.com/HelmholtzAI-Consultants-Munich/napari-organoid-counter#README.md
Project-URL: Source Code, https://github.com/HelmholtzAI-Consultants-Munich/napari-organoid-counter
Project-URL: User Support, https://github.com/HelmholtzAI-Consultants-Munich/napari-organoid-counter/issues
Classifier: Development Status :: 2 - Pre-Alpha
Classifier: Intended Audience :: Developers
Classifier: Framework :: napari
Classifier: Topic :: Software Development :: Testing
Classifier: Programming Language :: Python
Classifier: Programming Language :: Python :: 3
Classifier: Programming Language :: Python :: 3.8
Classifier: Programming Language :: Python :: 3.9
Classifier: Programming Language :: Python :: 3.10
Classifier: Operating System :: OS Independent
Classifier: License :: OSI Approved :: MIT License
Requires-Python: <3.11,>=3.9
License-File: LICENSE
Requires-Dist: napari[all]<0.5.0,>=0.4.17
Requires-Dist: napari-aicsimageio>=0.7.2
Requires-Dist: torch>=2.3.1
Requires-Dist: torchvision>=0.18.1
Requires-Dist: openmim
Requires-Dist: mmengine>=0.10.4
Requires-Dist: mmdet>=3.3.0
Provides-Extra: testing
Requires-Dist: tox; extra == "testing"
Requires-Dist: pytest; extra == "testing"
Requires-Dist: pytest-cov; extra == "testing"
Requires-Dist: pytest-qt; extra == "testing"
Requires-Dist: napari; extra == "testing"
Requires-Dist: pyqt5; extra == "testing"
